fmtm_splitter/__init__.py
fmtm_splitter/__version__.py
fmtm_splitter/db.py
fmtm_splitter/fmtm_algorithm.sql
fmtm_splitter/overpass.py
fmtm_splitter/raw.lua
fmtm_splitter/splitter.py
fmtm_splitter-2.0.0.dist-info/entry_points.txt
fmtm_splitter-2.0.0.dist-info/WHEEL
fmtm_splitter-2.0.0.dist-info/METADATA
fmtm_splitter-2.0.0.dist-info/licenses/LICENSE.md
fmtm_splitter-2.0.0.dist-info/RECORD
