Metadata-Version: 2.1
Name: fmtm-splitter
Version: 2.0.0
Summary: A utility for splitting an AOI into multiple tasks.
License: GPL-3.0-only
Keywords: fmtm,odk,hot
Author-email: Ivan Gayton <ivan.gayton@hotosm.org>,Rob Savoye <rob.savoye@hotosm.org>,Sam Woodcock <sam.woodcock@hotosm.org>,Sujan Adhikari <adhikarisujan.naxa@gmail.com>
Requires-Python: >=3.10
Classifier: Programming Language :: Python :: 3
Classifier: Programming Language :: Python :: 3.10
Classifier: Programming Language :: Python :: 3.11
Classifier: Topic :: Scientific/Engineering :: GIS
Classifier: Topic :: Utilities
Requires-Dist: geojson>=2.5.0
Requires-Dist: numpy>=1.21.0
Requires-Dist: osm-rawdata>=0.2.2
Requires-Dist: psycopg2>=2.9.1
Requires-Dist: shapely>=1.8.1
Project-URL: documentation, https://hotosm.github.io/fmtm-splitter
Project-URL: homepage, https://hotosm.github.io/fmtm-splitter
Project-URL: repository, https://github.com/hotosm/fmtm-splitter
